[{"id":"222e6aab.665f36","type":"tab","label":"Alexa home","disabled":false,"info":""},{"id":"eaf6d6c3.b3af78","type":"alexa-home-conf","z":"","username":"bebridge-tanibayashi"},{"id":"430f139.d4e13ec","type":"alexa-home","z":"222e6aab.665f36","conf":"eaf6d6c3.b3af78","device":"53989","acknoledge":true,"name":"ボールランプ","topic":"","x":110,"y":60,"wires":[["8d275469.f4cfc8","9fa8afed.1782a","1dd98f47.a40921"]]},{"id":"8d275469.f4cfc8","type":"debug","z":"222e6aab.665f36","name":"","active":true,"tosidebar":true,"console":false,"tostatus":true,"complete":"payload","targetType":"msg","x":530,"y":60,"wires":[]},{"id":"9fa8afed.1782a","type":"debug","z":"222e6aab.665f36","name":"","active":true,"tosidebar":true,"console":false,"tostatus":true,"complete":"command","targetType":"msg","x":320,"y":60,"wires":[]},{"id":"1dd98f47.a40921","type":"switch","z":"222e6aab.665f36","name":"コマンド分岐","property":"command","propertyType":"msg","rules":[{"t":"eq","v":"TurnOnRequest","vt":"str"},{"t":"eq","v":"TurnOffRequest","vt":"str"},{"t":"eq","v":"IncrementPercentageRequest","vt":"str"},{"t":"eq","v":"DecrementPercentageRequest","vt":"str"},{"t":"eq","v":"SetColorRequest","vt":"str"},{"t":"eq","v":"SetColorTemperatureRequest","vt":"str"}],"checkall":"true","repair":false,"outputs":6,"x":130,"y":220,"wires":[["58458238.576f8c"],["ab6f3dda.1aa26"],["78b8c820.974a18"],["96f71141.10ce8"],["8ee646df.ab2688"],["f34e6267.1d2f7"]]},{"id":"7e0d84a9.dbf6ac","type":"exec","z":"222e6aab.665f36","command":"/home/pi/bin/ir-send","addpay":true,"append":"","useSpawn":"true","timer":"","oldrc":false,"name":"","x":690,"y":360,"wires":[["7591405d.dd2d8"],["7591405d.dd2d8"],[]]},{"id":"59459aa4.722704","type":"change","z":"222e6aab.665f36","name":"\"lamp {p}\"","rules":[{"t":"set","p":"payload","pt":"msg","to":"\"lamp \" & msg.payload","tot":"jsonata"}],"action":"","property":"","from":"","to":"","reg":false,"x":620,"y":280,"wires":[["7e0d84a9.dbf6ac","9c426dc2.dcf97"]]},{"id":"9c426dc2.dcf97","type":"debug","z":"222e6aab.665f36","name":"","active":true,"tosidebar":true,"console":false,"tostatus":true,"complete":"payload","targetType":"msg","x":810,"y":280,"wires":[]},{"id":"58458238.576f8c","type":"change","z":"222e6aab.665f36","name":"on","rules":[{"t":"set","p":"payload","pt":"msg","to":"on","tot":"str"}],"action":"","property":"","from":"","to":"","reg":false,"x":330,"y":140,"wires":[["e58d4312.243cb"]]},{"id":"ab6f3dda.1aa26","type":"change","z":"222e6aab.665f36","name":"off","rules":[{"t":"set","p":"payload","pt":"msg","to":"off","tot":"str"}],"action":"","property":"","from":"","to":"","reg":false,"x":330,"y":180,"wires":[["e58d4312.243cb"]]},{"id":"7591405d.dd2d8","type":"debug","z":"222e6aab.665f36","name":"","active":true,"tosidebar":true,"console":false,"tostatus":true,"complete":"payload","targetType":"msg","x":890,"y":360,"wires":[]},{"id":"8ee646df.ab2688","type":"switch","z":"222e6aab.665f36","name":"hue","property":"payload.hue","propertyType":"msg","rules":[{"t":"eq","v":"0","vt":"num"},{"t":"eq","v":"120","vt":"str"},{"t":"eq","v":"240","vt":"str"}],"checkall":"true","repair":false,"outputs":3,"x":190,"y":360,"wires":[["bd6db33.2e7505"],["f3f28191.27dca"],["310b177e.801cb8"]]},{"id":"bd6db33.2e7505","type":"change","z":"222e6aab.665f36","name":"red","rules":[{"t":"set","p":"payload","pt":"msg","to":"red","tot":"str"}],"action":"","property":"","from":"","to":"","reg":false,"x":330,"y":320,"wires":[["b6f5a0e3.708b9"]]},{"id":"f3f28191.27dca","type":"change","z":"222e6aab.665f36","name":"green","rules":[{"t":"set","p":"payload","pt":"msg","to":"green","tot":"str"}],"action":"","property":"","from":"","to":"","reg":false,"x":330,"y":360,"wires":[["b6f5a0e3.708b9"]]},{"id":"310b177e.801cb8","type":"change","z":"222e6aab.665f36","name":"blue","rules":[{"t":"set","p":"payload","pt":"msg","to":"blue","tot":"str"}],"action":"","property":"","from":"","to":"","reg":false,"x":330,"y":400,"wires":[["b6f5a0e3.708b9"]]},{"id":"f34e6267.1d2f7","type":"switch","z":"222e6aab.665f36","name":"color temperature","property":"payload","propertyType":"msg","rules":[{"t":"eq","v":"4000","vt":"num"}],"checkall":"true","repair":false,"outputs":1,"x":150,"y":440,"wires":[["9f4b8512.4a7d28"]]},{"id":"9f4b8512.4a7d28","type":"change","z":"222e6aab.665f36","name":"white","rules":[{"t":"set","p":"payload","pt":"msg","to":"white","tot":"str"}],"action":"","property":"","from":"","to":"","reg":false,"x":330,"y":440,"wires":[["c1a60e5.febcff"]]},{"id":"e58d4312.243cb","type":"batch","z":"222e6aab.665f36","name":"","mode":"count","count":"1","overlap":0,"interval":10,"allowEmptySequence":false,"topics":[],"x":470,"y":200,"wires":[["59459aa4.722704"]]},{"id":"b6f5a0e3.708b9","type":"batch","z":"222e6aab.665f36","name":"","mode":"count","count":"1","overlap":0,"interval":10,"allowEmptySequence":false,"topics":[],"x":470,"y":360,"wires":[["59459aa4.722704"]]},{"id":"78b8c820.974a18","type":"change","z":"222e6aab.665f36","name":"up2","rules":[{"t":"set","p":"payload","pt":"msg","to":"up2","tot":"str"}],"action":"","property":"","from":"","to":"","reg":false,"x":330,"y":220,"wires":[["e58d4312.243cb"]]},{"id":"96f71141.10ce8","type":"change","z":"222e6aab.665f36","name":"down2","rules":[{"t":"set","p":"payload","pt":"msg","to":"down2","tot":"str"}],"action":"","property":"","from":"","to":"","reg":false,"x":330,"y":260,"wires":[["e58d4312.243cb"]]},{"id":"c1a60e5.febcff","type":"batch","z":"222e6aab.665f36","name":"","mode":"count","count":"1","overlap":0,"interval":10,"allowEmptySequence":false,"topics":[],"x":470,"y":440,"wires":[["59459aa4.722704"]]}]